Workbook

Sheet Chart of Accounts
A1: Account Number | B1: Account Name | C1: Account Type
A2: 101 | B2: Cash | C2: Asset
A3: 105 | B3: Accounts Receivable | C3: Asset
A4: 110 | B4: Inventory | C4: Asset
A5: 120 | B5: Prepaid Expenses | C5: Asset
A6: 160 | B6: Equipment | C6: Asset
A7: 201 | B7: Accounts Payable | C7: Liability
A8: 210 | B8: Credit Card Payable | C8: Liability
A9: 300 | B9: Owner's Equity | C9: Equity
A10: 310 | B10: Owner's Contribution | C10: Equity
A11: 400 | B11: Product Sales | C11: Revenue
A12: 501 | B12: Cost of Good Sold | C12: Expense
A13: 510 | B13: Marketing Expense | C13: Expense
... A16: 540 | B16: Shipping Expense | C16: Expense

Sheet Journal Entries
A1: Date | B1: Account Number | C1: Account Name | D1: Debit | E1: Credit | F1: Description
A2: 45658 | B2: 101 | C2: Cash | D2: 5000 | F2: Owner contribution
A3: 45658 | B3: 310 | C3: Owner's Contributions | E3: 5000 | F3: Owner contribution
A4: 45660 | B4: 110 | C4: Inventory | D4: 1200 | F4: Inventory purchase
A5: 45660 | B5: 101 | C5: Cash | E5: 1200 | F5: Inventory purchase
A6: 45664 | B6: 101 | C6: Cash | D6: 2000 | F6: Products sales
A7: 45664 | B7: 400 | C7: Product Sales | E7: 2000 | F7: Products sales
A8: 45666 | B8: 510 | C8: Marketing Expense | D8: 150 | F8: Ad spend
A9: 45666 | B9: 210 | C9: Credit Card Payable | E9: 150 | F9: Ad spend
A10: 45667 | B10: 501 | C10: Cost of Goods Sold | D10: 400 | F10: Inventory used
A11: 45667 | B11: 110 | C11: Inventory | E11: 400 | F11: Inventory used
A12: 45669 | B12: 540 | C12: Shipping Expense | D12: 85 | F12: Shipping
A13: 45669 | B13: 101 | C13: Cash | E13: 85 | F13: Shipping
A14: 45671 | B14: 520 | C14: Software Subscription | D14: 35 | F14: Software
A15: 45671 | B15: 101 | C15: Cash | E15: 35 | F15: Software
A16: 45677 | B16: 160 | C16: Equipment | D16: 800 | F16: Equipment Purchase
A17: 45677 | B17: 101 | C17: Cash | E17: 800 | F17: Equipment
A18: 45683 | B18: 101 | C18: Cash | D18: 3000 | F18: Products sales
A19: 45683 | B19: 400 | C19: Product Sales | E19: 3000 | F19: Products sales
A20: 45686 | B20: 530 | C20: Supplies Expense | D20: 60 | F20: Supplies
A21: 45686 | B21: 101 | C21: Cash | E21: 60 | F21: Supplies

Sheet General Ledger
A1: Account Number | B1: Account Name | C1: Debit Total | D1: Credit Total | E1: Balance
A2: 101 | B2: Cash | C2: =SUMIFS('Journal Entries'!D:D,'Journal Entries'!B:B,A2) -> 10000 | D2: =SUMIFS('Journal Entries'!E:E,'Journal Entries'!B:B,A2) -> 2180 | E2: =C2-D2 -> 7820
A3: 105 | B3: Accounts Receivable | C3: =SUMIFS('Journal Entries'!D:D,'Journal Entries'!B:B,A3) -> 0 | D3: =SUMIFS('Journal Entries'!E:E,'Journal Entries'!B:B,A3) -> 0 | E3: =C3-D3 -> 0
A4: 110 | B4: Inventory | C4: =SUMIFS('Journal Entries'!D:D,'Journal Entries'!B:B,A4) -> 1200 | D4: =SUMIFS('Journal Entries'!E:E,'Journal Entries'!B:B,A4) -> 400 | E4: =C4-D4 -> 800
A5: 120 | B5: Prepaid Expenses | C5: =SUMIFS('Journal Entries'!D:D,'Journal Entries'!B:B,A5) -> 0 | D5: =SUMIFS('Journal Entries'!E:E,'Journal Entries'!B:B,A5) -> 0 | E5: =C5-D5 -> 0
A6: 160 | B6: Equipment | C6: =SUMIFS('Journal Entries'!D:D,'Journal Entries'!B:B,A6) -> 800 | D6: =SUMIFS('Journal Entries'!E:E,'Journal Entries'!B:B,A6) -> 0 | E6: =C6-D6 -> 800
A7: 201 | B7: Accounts Payable | C7: =SUMIFS('Journal Entries'!D:D,'Journal Entries'!B:B,A7) -> 0 | D7: =SUMIFS('Journal Entries'!E:E,'Journal Entries'!B:B,A7) -> 0 | E7: =C7-D7 -> 0
A8: 210 | B8: Credit Card Payable | C8: =SUMIFS('Journal Entries'!D:D,'Journal Entries'!B:B,A8) -> 0 | D8: =SUMIFS('Journal Entries'!E:E,'Journal Entries'!B:B,A8) -> 150 | E8: =C8-D8 -> -150
A9: 300 | B9: Owner's Equity | C9: =SUMIFS('Journal Entries'!D:D,'Journal Entries'!B:B,A9) -> 0 | D9: =SUMIFS('Journal Entries'!E:E,'Journal Entries'!B:B,A9) -> 0 | E9: =C9-D9 -> 0
A10: 310 | B10: Owner's Contributions | C10: =SUMIFS('Journal Entries'!D:D,'Journal Entries'!B:B,A10) -> 0 | D10: =SUMIFS('Journal Entries'!E:E,'Journal Entries'!B:B,A10) -> 5000 | E10: =C10-D10 -> -5000
A11: 400 | B11: Product Sales | C11: =SUMIFS('Journal Entries'!D:D,'Journal Entries'!B:B,A11) -> 0 | D11: =SUMIFS('Journal Entries'!E:E,'Journal Entries'!B:B,A11) -> 5000 | E11: =C11-D11 -> -5000
A12: 501 | B12: Cost of Goods Sold | C12: =SUMIFS('Journal Entries'!D:D,'Journal Entries'!B:B,A12) -> 400 | D12: =SUMIFS('Journal Entries'!E:E,'Journal Entries'!B:B,A12) -> 0 | E12: =C12-D12 -> 400
A13: 510 | B13: Marketing Expense | C13: =SUMIFS('Journal Entries'!D:D,'Journal Entries'!B:B,A13) -> 150 | D13: =SUMIFS('Journal Entries'!E:E,'Journal Entries'!B:B,A13) -> 0 | E13: =C13-D13 -> 150
... A16: 540 | B16: Shipping Expense | C16: =SUMIFS('Journal Entries'!D:D,'Journal Entries'!B:B,A16) -> 85 | D16: =SUMIFS('Journal Entries'!E:E,'Journal Entries'!B:B,A16) -> 0 | E16: =C16-D16 -> 85

Sheet Trial Balance
A1: Account Name | B1: Debit | C1: Credit
A2: Cash | B2: =IF('General Ledger'!E2>0,'General Ledger'!E2,"") -> 7820 | C2: =IF('General Ledger'!E2<0,ABS('General Ledger'!E2),"")
A3: Accounts Receivable | B3: =IF('General Ledger'!E3>0,'General Ledger'!E3,"") | C3: =IF('General Ledger'!E3<0,ABS('General Ledger'!E3),"")
A4: Inventory | B4: =IF('General Ledger'!E4>0,'General Ledger'!E4,"") -> 800 | C4: =IF('General Ledger'!E4<0,ABS('General Ledger'!E4),"")
A5: Prepaid Expenses | B5: =IF('General Ledger'!E5>0,'General Ledger'!E5,"") | C5: =IF('General Ledger'!E5<0,ABS('General Ledger'!E5),"")
A6: Equipment | B6: =IF('General Ledger'!E6>0,'General Ledger'!E6,"") -> 800 | C6: =IF('General Ledger'!E6<0,ABS('General Ledger'!E6),"")
A7: Accounts Payable | B7: =IF('General Ledger'!E7>0,'General Ledger'!E7,"") | C7: =IF('General Ledger'!E7<0,ABS('General Ledger'!E7),"")
A8: Credit Card Payable | B8: =IF('General Ledger'!E8>0,'General Ledger'!E8,"") | C8: =IF('General Ledger'!E8<0,ABS('General Ledger'!E8),"") -> 150
A9: Owner's Equity | B9: =IF('General Ledger'!E9>0,'General Ledger'!E9,"") | C9: =IF('General Ledger'!E9<0,ABS('General Ledger'!E9),"")
A10: Owner's Contributions | B10: =IF('General Ledger'!E10>0,'General Ledger'!E10,"") | C10: =IF('General Ledger'!E10<0,ABS('General Ledger'!E10),"") -> 5000
A11: Product Sales | B11: =IF('General Ledger'!E11>0,'General Ledger'!E11,"") | C11: =IF('General Ledger'!E11<0,ABS('General Ledger'!E11),"") -> 5000
A12: Cost of Goods Sold | B12: =IF('General Ledger'!E12>0,'General Ledger'!E12,"") -> 400 | C12: =IF('General Ledger'!E12<0,ABS('General Ledger'!E12),"")
A13: Marketing Expense | B13: =IF('General Ledger'!E13>0,'General Ledger'!E13,"") -> 150 | C13: =IF('General Ledger'!E13<0,ABS('General Ledger'!E13),"")
... A16: Shipping Expense | B16: =IF('General Ledger'!E16>0,'General Ledger'!E16,"") -> 85 | C16: =IF('General Ledger'!E16<0,ABS('General Ledger'!E16),"")
A18: Total | B18: =SUM(B2:B16) -> 10150 | C18: =SUM(C2:C16) -> 10150

Sheet Income Statement 
A1: LuxeGlow Skincare
A2: Income Statement
A3: For Month Ended January 31,2025
A5: Revenue
A6: Product Sales | B6: =ABS('Trial Balance'!C11) -> 5000
A7: Total Revenue | B7: =SUM(B6) -> 5000
A9: Expenses
A10: Cost of Goods Sold | B10: =SUMIF('Trial Balance'!A:A,A10,'Trial Balance'!B:B) -> 400
A11: Marketing Expense | B11: =SUMIF('Trial Balance'!A:A,A11,'Trial Balance'!B:B) -> 150
A12: Software Subscriptions | B12: =SUMIF('Trial Balance'!A:A,A12,'Trial Balance'!B:B) -> 35
A13: Supplies Expense | B13: =SUMIF('Trial Balance'!A:A,A13,'Trial Balance'!B:B) -> 60
A14: Shipping Expense | B14: =SUMIF('Trial Balance'!A:A,A14,'Trial Balance'!B:B) -> 85
A15: Total Expense | B15: =SUM(B10:B14) -> 730
A17: Net Income | B17: =B7-B15 -> 4270

Sheet Balance Sheet
A1: Assets
A2: Cash | B2: =ABS('Trial Balance'!B2) -> 7820
A3: Accounts Receivable | B3: 0
A4: Inventory | B4: =ABS('Trial Balance'!B4) -> 800
A5: Prepaid Expenses | B5: 0
A6: Equipment | B6: =ABS('Trial Balance'!B6) -> 800
A8: Total | C8: =(B2+B3+B4+B5+B6) -> 9420
A9: Liabilities
A10: Accounts Payable | B10: 0
A11: Credit Card Payable | B11: =ABS('Trial Balance'!C8) -> 150
A13: Total | C13: =(B10+B11) -> 150
A14: Equity
A15: Owner's Contributions | B15: =ABS('Trial Balance'!C10) -> 5000
A16: Retained Earnings | B16: =ABS('Income Statement '!B17) -> 4270
A18: Total | C18: =(B15+B16) -> 9270
A20: Total Assets | B20: =C13+C18 -> 9420

Sheet Dashboard 
A1: LuxeGlow Skincare
A2: January 2025 Finacial Dashboard
D5: Expense Category | E5: Amount
A6: Total Revenue | B6: ='Income Statement '!B7 -> 5000 | D6: COGS | E6: ='Trial Balance'!B12 -> 400
A7: Total Expenses | B7: ='Income Statement '!B15 -> 730 | D7: Marketing | E7: ='Trial Balance'!B13 -> 150
A8: Net Income | B8: =B6-B7 -> 4270 | D8: Software | E8: ='Trial Balance'!B14 -> 35
A9: Ending Cash Balance | B9: =SUMIF('Trial Balance'!A:A,"Cash",'Trial Balance'!B:B) -> 7820 | D9: Supplies | E9: ='Trial Balance'!B15 -> 60
D10: Shipping | E10: ='Trial Balance'!B16 -> 85
D13: Category | E13: Amount
D14: Revenue | E14: ='Income Statement '!B7 -> 5000
D15: Expense | E15: ='Income Statement '!B15 -> 730
